findus/AnalogPlot.py
findus/DebugInterface.py
findus/ExternalPowerSupply.py
findus/GeneticAlgorithm.py
findus/GlitchState.py
findus/HuskyGlitcher.py
findus/InteractivePchipEditor.py
findus/ProGlitcher.py
findus/STM32Bootloader.py
findus/STM8Programmer.py
findus/__init__.py
findus/findus.py
findus/pyboard.py
findus/analyzer/__init__.py
findus/analyzer/analyzer.py
findus/analyzer/analyzer_new.py
findus/firmware/AD910X.py
findus/firmware/FastADC.py
findus/firmware/Globals.py
findus/firmware/PicoGlitcher.py
findus/firmware/PulseGenerator.py
findus/firmware/Spline.py
findus/firmware/Statemachines.py
findus/firmware/__init__.py
findus/firmware/decorators.py
findus/firmware/config_v1/config.json
findus/firmware/config_v2.1-2/config.json
findus/firmware/config_v2.3-4/config.json
findus/helper/__init__.py
findus/helper/database_tool.py
findus/helper/power_cycle.py
findus/helper/power_on.py
findus/helper/pulse_shaping_calibration.py
findus/helper/stm32_power_cycle_and_read.py
findus/helper/upload.py
findus-1.12.1.dist-info/licenses/LICENSE
findus-1.12.1.dist-info/METADATA
findus-1.12.1.dist-info/WHEEL
findus-1.12.1.dist-info/entry_points.txt
findus-1.12.1.dist-info/top_level.txt
findus-1.12.1.dist-info/RECORD
