Metadata-Version: 2.4
Name: findus
Version: 1.12.1
Summary: Library to perform fault injection attacks with the PicoGlitcher, Chipwhisperer Husky or Chipwhisperer Pro
Author-email: Matthias Kesenheimer <m.kesenheimer@gmx.net>
Project-URL: Homepage, https://mkesenheimer.github.io
Project-URL: Documentation, https://fault-injection-library.readthedocs.io/en/latest/
Project-URL: Repository, https://github.com/MKesenheimer/fault-injection-library.git
Project-URL: Issues, https://github.com/MKesenheimer/fault-injection-library/issues
License-File: LICENSE
Requires-Dist: setuptools
Requires-Dist: adafruit-ampy
Requires-Dist: pyserial
Requires-Dist: plotly
Requires-Dist: pandas
Requires-Dist: dash
Requires-Dist: dash_bootstrap_components
Requires-Dist: dash_ag_grid
Requires-Dist: matplotlib
Requires-Dist: scipy
Dynamic: license-file
